genius_chatbot/__init__.py
genius_chatbot/genius_chatbot.py
genius_chatbot/version.py
genius_chatbot-1.10.4.dist-info/LICENSE
genius_chatbot-1.10.4.dist-info/METADATA
genius_chatbot-1.10.4.dist-info/WHEEL
genius_chatbot-1.10.4.dist-info/entry_points.txt
genius_chatbot-1.10.4.dist-info/top_level.txt
genius_chatbot-1.10.4.dist-info/RECORD
