Metadata-Version: 2.1
Name: genius-chatbot
Version: 1.10.4
Summary: Use huggingface models to create an intelligent and scalable chatbot
Home-page: https://github.com/Knuckles-Team/genius-chatbot
Author: Audel Rouhi
Author-email: knucklessg1@gmail.com
Maintainer: Audel Rouhi
Maintainer-email: knucklessg1@gmail.com
License: MIT
Platform: UNKNOWN
Classifier: Development Status :: 5 - Production/Stable
Classifier: License :: Public Domain
Classifier: Environment :: Console
Classifier: Operating System :: POSIX :: Linux
Classifier: Programming Language :: Python :: 3.8
Classifier: Programming Language :: Python :: 3.9
Classifier: Programming Language :: Python :: 3.10
Classifier: Programming Language :: Python :: 3.11
Classifier: Programming Language :: Python :: 3.12
License-File: LICENSE
Requires-Dist: EbookLib (>=0.18)
Requires-Dist: Markdown (>=3.5.2)
Requires-Dist: PyMuPDF (>=1.23.22)
Requires-Dist: appengine-python-standard (>=1.1.6)
Requires-Dist: chromadb (>=0.4.24)
Requires-Dist: docx2txt (>=0.8)
Requires-Dist: extract-msg (>=0.47.0)
Requires-Dist: gpt4all (>=2.2.1.post1)
Requires-Dist: langchain-community (>=0.0.24)
Requires-Dist: langchain (>=0.1.9)
Requires-Dist: llama-cpp-python (>=0.2.53)
Requires-Dist: nltk (>=3.8.1)
Requires-Dist: openai (>=1.12.0)
Requires-Dist: pandoc (>=2.3)
Requires-Dist: pgvector (>=0.2.5)
Requires-Dist: psutil (>=5.9.8)
Requires-Dist: psycopg-binary (>=3.1.18)
Requires-Dist: pydantic (>=2.6.3)
Requires-Dist: pypandoc (>=1.13)
Requires-Dist: sentence-transformers (>=2.3.1)
Requires-Dist: tabulate (>=0.9.0)
Requires-Dist: tiktoken (>=0.6.0)
Requires-Dist: tqdm (>=4.66.2)
Requires-Dist: unstructured[all-docs] (>=0.12.5)
